euc/kingsong/__init__.py
euc/kingsong/kingsong.py
euc.kingsong-0.2.0.dist-info/LICENSE
euc.kingsong-0.2.0.dist-info/METADATA
euc.kingsong-0.2.0.dist-info/WHEEL
euc.kingsong-0.2.0.dist-info/entry_points.txt
euc.kingsong-0.2.0.dist-info/top_level.txt
euc.kingsong-0.2.0.dist-info/zip-safe
euc.kingsong-0.2.0.dist-info/RECORD
