Metadata-Version: 2.1
Name: euc.kingsong
Version: 0.2.0
Summary: python library for KingSong Electric Unicycles
Home-page: https://github.com/mrk-its/euc.kingsong
Author: Mariusz Kryński
Author-email: mrk@sed.pl
License: MIT
Keywords: euc,dbussy,kingsong
Platform: any
Classifier: Development Status :: 4 - Beta
Classifier: Intended Audience :: Developers
Classifier: License :: OSI Approved :: MIT License
Classifier: Operating System :: POSIX :: Linux
Classifier: Programming Language :: Python
Classifier: Programming Language :: Python :: 3.6
Classifier: Programming Language :: Python :: 3.7
Classifier: Programming Language :: Python :: 3.8
Classifier: Topic :: Software Development :: Libraries :: Python Modules
Requires-Python: >= 2.7, != 3.0.*, != 3.1.*, != 3.2.*, != 3.3.*, != 3.5.*
Requires-Dist: euc (>=0.2.0)
Provides-Extra: dev
Requires-Dist: black ; extra == 'dev'
Requires-Dist: flake8 ; extra == 'dev'
Provides-Extra: tests
